{
  "success": true,
  "data": {
    "page": 1,
    "limit": 100,
    "total": 6,
    "goods": [
      {
        "c_id": "a32f04d8-a874-489c-bed6-e1859a03c0ae",
        "c_description": "Худи черное, цветная вышивка на спине -значок компании, спереди - значок компании\nЦвет: черный \nМатериал: хлопок 100%, плотность 320 г/м²; футер трехнитка Размер: L\nОбъём ёмкости: 320 г/м2\n",
        "c_comment": "",
        "c_priceWithTax": 0.0,
        "c_count": 75.0,
        "c_tax": 0.0,
        "c_priceWithoutTax": 0.0,
        "c_okpd2Code": null,
        "c_okpd2Name": null,
        "c_warrantyPeriodMonths": null,
        "c_hasDistinctName": false,
        "c_unitId": "cfb3e723-63f1-4fb4-a7f9-6c7a09f3bebd",
        "c_unitName": "шт",
        "c_unitOkeiCode": "796",
        "c_code": null,
        "c_attachments": []
      },
      {
        "c_id": "4ec4b1a9-d8f1-43a3-8f74-f09de862c1fb",
        "c_description": "Худи серо-голубое, цветная вышивка на спине - значок компании, спереди - значок компании\nМатериал: хлопок 65%; полиэстер 35%, плотность 350 г/м²; трехнитка, гребенной хлопок\n(пенье) Размер: M;L\nОбъём ёмкости: 350 г/м2\n",
        "c_comment": "",
        "c_priceWithTax": 0.0,
        "c_count": 10.0,
        "c_tax": 0.0,
        "c_priceWithoutTax": 0.0,
        "c_okpd2Code": null,
        "c_okpd2Name": null,
        "c_warrantyPeriodMonths": null,
        "c_hasDistinctName": false,
        "c_unitId": "cfb3e723-63f1-4fb4-a7f9-6c7a09f3bebd",
        "c_unitName": "шт",
        "c_unitOkeiCode": "796",
        "c_code": null,
        "c_attachments": []
      },
      {
        "c_id": "25c91aff-2e1e-4cb5-9567-241dc193de85",
        "c_description": "Свитшот салатовый, цветная вышивка на спине -значок компании, спереди значок - компании\nЦвет: зеленое яблоко Вес: 430 г.\nМатериал: 50% хлопок 50% полиэстер Размер: M\nОбъём ёмкости: 280±10 г/м2\n",
        "c_comment": "",
        "c_priceWithTax": 0.0,
        "c_count": 10.0,
        "c_tax": 0.0,
        "c_priceWithoutTax": 0.0,
        "c_okpd2Code": null,
        "c_okpd2Name": null,
        "c_warrantyPeriodMonths": null,
        "c_hasDistinctName": false,
        "c_unitId": "cfb3e723-63f1-4fb4-a7f9-6c7a09f3bebd",
        "c_unitName": "шт",
        "c_unitOkeiCode": "796",
        "c_code": null,
        "c_attachments": []
      },
      {
        "c_id": "c11ffbf1-a15c-4d51-906f-882a0916f39f",
        "c_description": "Варежки\nЦвет: серый; серый меланж Вес: 120.00 г.\nМатериал: акрил 100% Размер: S;M\n",
        "c_comment": "",
        "c_priceWithTax": 0.0,
        "c_count": 50.0,
        "c_tax": 0.0,
        "c_priceWithoutTax": 0.0,
        "c_okpd2Code": null,
        "c_okpd2Name": null,
        "c_warrantyPeriodMonths": null,
        "c_hasDistinctName": false,
        "c_unitId": "cfb3e723-63f1-4fb4-a7f9-6c7a09f3bebd",
        "c_unitName": "шт",
        "c_unitOkeiCode": "796",
        "c_code": null,
        "c_attachments": []
      },
      {
        "c_id": "ae1405a5-8254-41e9-98dc-86a8531fda2f",
        "c_description": "Пакет бумажный 35 * 30, с надписью компании\nПакет из бумаги Snow White Kraft, 160 г/м²",
        "c_comment": "",
        "c_priceWithTax": 0.0,
        "c_count": 50.0,
        "c_tax": 0.0,
        "c_priceWithoutTax": 0.0,
        "c_okpd2Code": null,
        "c_okpd2Name": null,
        "c_warrantyPeriodMonths": null,
        "c_hasDistinctName": false,
        "c_unitId": "cfb3e723-63f1-4fb4-a7f9-6c7a09f3bebd",
        "c_unitName": "шт",
        "c_unitOkeiCode": "796",
        "c_code": null,
        "c_attachments": []
      },
      {
        "c_id": "733cc105-212f-461d-bd4a-79e859ec796d",
        "c_description": "Плед, серый/черный- шифрон компании\nМатериал: хлопок 95%, полиэстер 5%, плотность 300 г/м²\nОбъём ёмкости: 300 г/м2\nГабариты: 130x170 см (с кистями); в сложении: 37x30x5 см Вес: 786.67 г.\n",
        "c_comment": "",
        "c_priceWithTax": 0.0,
        "c_count": 50.0,
        "c_tax": 0.0,
        "c_priceWithoutTax": 0.0,
        "c_okpd2Code": null,
        "c_okpd2Name": null,
        "c_warrantyPeriodMonths": null,
        "c_hasDistinctName": false,
        "c_unitId": "cfb3e723-63f1-4fb4-a7f9-6c7a09f3bebd",
        "c_unitName": "шт",
        "c_unitOkeiCode": "796",
        "c_code": null,
        "c_attachments": []
      }
    ]
  }
}