{
  "success": true,
  "data": {
    "page": 1,
    "limit": 100,
    "total": 1,
    "goods": [
      {
        "c_id": "28b9be9f-faad-4903-a27e-e78ed23c79fb",
        "c_description": "Ноутбук",
        "c_comment": "HP Модель: EliteBook 840 G11 (A36XTET) \nКоличество: 2 шт. \nВ техническом задании*",
        "c_priceWithTax": 125941.25,
        "c_count": 2.0,
        "c_tax": 0.0,
        "c_priceWithoutTax": 125941.25,
        "c_okpd2Code": "26.20.11.110",
        "c_okpd2Name": "Компьютеры портативные массой не более 10 кг, такие как ноутбуки, планшетные компьютеры, карманные компьютеры, в том числе совмещающие функции мобильного телефонного аппарата",
        "c_warrantyPeriodMonths": 12,
        "c_hasDistinctName": false,
        "c_unitId": "cfb3e723-63f1-4fb4-a7f9-6c7a09f3bebd",
        "c_unitName": "шт",
        "c_unitOkeiCode": "796",
        "c_code": null,
        "c_attachments": [
          {
            "id": "208d7795-17ae-4a06-8659-99af38be8d4b",
            "is_deletable": true,
            "name": "933c828cd26d79849b8480a75e443ed2.docx",
            "original_name": "Техническое задание.docx",
            "size": 19250,
            "type": "document",
            "web_path": "/uploads/documents/93/3c8/28c/",
            "created_at": "2025-10-02T15:07:01+03:00",
            "created_by": {
              "name": "Анна",
              "patronymic": "Андреевна",
              "surname": "Постолова"
            },
            "file": {
              "id": "17e04d3e-7acc-479c-bac0-f68f01a627f9",
              "name": "933c828cd26d79849b8480a75e443ed2.docx",
              "original_name": "Техническое задание.docx",
              "type": "application/vnd.openxmlformats-officedocument.wordprocessingml.document",
              "web_path": "/uploads/documents/93/3c8/28c/"
            }
          }
        ]
      }
    ]
  }
}